pdf_unlocker/__init__.py
pdf_unlocker/__main__.py
pdf_unlocker-1.3.dist-info/METADATA
pdf_unlocker-1.3.dist-info/WHEEL
pdf_unlocker-1.3.dist-info/entry_points.txt
pdf_unlocker-1.3.dist-info/top_level.txt
pdf_unlocker-1.3.dist-info/RECORD
