Metadata-Version: 2.1
Name: pdf-unlocker
Version: 1.3
Home-page: https://github.com/jfhack/pdf-unlocker
Requires-Dist: pikepdf
